README.md
setup.py
dsnd2_distro/Binomialdistribution.py
dsnd2_distro/Gaussiandistribution.py
dsnd2_distro/Generaldistribution.py
dsnd2_distro/__init__.py
dsnd2_distro.egg-info/PKG-INFO
dsnd2_distro.egg-info/SOURCES.txt
dsnd2_distro.egg-info/dependency_links.txt
dsnd2_distro.egg-info/not-zip-safe
dsnd2_distro.egg-info/top_level.txt