Metadata-Version: 1.0
Name: dsnd2-distro
Version: 0.7
Summary: Gaussian distributions
Home-page: UNKNOWN
Author: UNKNOWN
Author-email: UNKNOWN
License: UNKNOWN
Platform: UNKNOWN
